{"nodes": [{"id": "corpo_omnes_site_js_evenements_js", "label": "evenements.js", "file_type": "code", "source_file": "corpo-omnes-site\\js\\evenements.js", "source_location": "L1"}, {"id": "evenements_renderevents", "label": "renderEvents()", "file_type": "code", "source_file": "corpo-omnes-site\\js\\evenements.js", "source_location": "L16"}], "edges": [{"source": "corpo_omnes_site_js_evenements_js", "target": "evenements_renderevents", "relation": "contains", "confidence": "EXTRACTED", "source_file": "corpo-omnes-site\\js\\evenements.js", "source_location": "L16", "weight": 1.0}], "raw_calls": [{"caller_nid": "evenements_renderevents", "callee": "getEvenements", "source_file": "corpo-omnes-site\\js\\evenements.js", "source_location": "L19"}, {"caller_nid": "evenements_renderevents", "callee": "forEach", "source_file": "corpo-omnes-site\\js\\evenements.js", "source_location": "L30"}]}